[
    {
        "codigo": "UX350",
        "origen": "Sevilla",
        "destino": "Madrid",
        "fecha_salida": "2025-10-27",
        "hora_salida": "23:58",
        "duracion": 88
    },
    {
        "codigo": "IB704",
        "origen": "Bilbao",
        "destino": "Sevilla",
        "fecha_salida": "2025-04-05",
        "hora_salida": "21:45",
        "duracion": 114
    },
    {
        "codigo": "IB323",
        "origen": "Barcelona",
        "destino": "Madrid",
        "fecha_salida": "2025-03-03",
        "hora_salida": "09:11",
        "duracion": 89
    },
    {
        "codigo": "VY833",
        "origen": "Toledo",
        "destino": "Madrid",
        "fecha_salida": "2025-12-06",
        "hora_salida": "15:50",
        "duracion": 143
    },
    {
        "codigo": "VY559",
        "origen": "Ceuta",
        "destino": "Vitoria",
        "fecha_salida": "2025-06-08",
        "hora_salida": "11:32",
        "duracion": 135
    },
    {
        "codigo": "VY814",
        "origen": "Palma de Mallorca",
        "destino": "Madrid",
        "fecha_salida": "2025-05-27",
        "hora_salida": "18:38",
        "duracion": 114
    },
    {
        "codigo": "VY320",
        "origen": "Oviedo",
        "destino": "Palma de Mallorca",
        "fecha_salida": "2025-05-19",
        "hora_salida": "08:33",
        "duracion": 157
    },
    {
        "codigo": "IB489",
        "origen": "Oviedo",
        "destino": "Sevilla",
        "fecha_salida": "2025-04-16",
        "hora_salida": "20:40",
        "duracion": 72
    },
    {
        "codigo": "UX926",
        "origen": "Santa Cruz de Tenerife",
        "destino": "Pamplona",
        "fecha_salida": "2025-12-04",
        "hora_salida": "16:29",
        "duracion": 65
    },
    {
        "codigo": "IB487",
        "origen": "Logrono",
        "destino": "Melilla",
        "fecha_salida": "2025-04-02",
        "hora_salida": "11:24",
        "duracion": 70
    },
    {
        "codigo": "UX691",
        "origen": "Ceuta",
        "destino": "Las Palmas de Gran Canaria",
        "fecha_salida": "2025-11-11",
        "hora_salida": "11:22",
        "duracion": 84
    },
    {
        "codigo": "VY891",
        "origen": "Valencia",
        "destino": "Barcelona",
        "fecha_salida": "2025-12-06",
        "hora_salida": "07:36",
        "duracion": 97
    },
    {
        "codigo": "IB489",
        "origen": "Valencia",
        "destino": "Palma de Mallorca",
        "fecha_salida": "2026-02-03",
        "hora_salida": "03:47",
        "duracion": 95
    },
    {
        "codigo": "VY479",
        "origen": "Logrono",
        "destino": "Santa Cruz de Tenerife",
        "fecha_salida": "2025-09-21",
        "hora_salida": "11:16",
        "duracion": 105
    },
    {
        "codigo": "IB723",
        "origen": "Zaragoza",
        "destino": "Las Palmas de Gran Canaria",
        "fecha_salida": "2025-03-27",
        "hora_salida": "10:24",
        "duracion": 141
    },
    {
        "codigo": "VY267",
        "origen": "Malaga",
        "destino": "Melilla",
        "fecha_salida": "2025-10-08",
        "hora_salida": "23:52",
        "duracion": 119
    },
    {
        "codigo": "VY801",
        "origen": "Pamplona",
        "destino": "Palma de Mallorca",
        "fecha_salida": "2025-08-04",
        "hora_salida": "12:40",
        "duracion": 101
    },
    {
        "codigo": "IB924",
        "origen": "Barcelona",
        "destino": "Palma de Mallorca",
        "fecha_salida": "2025-03-06",
        "hora_salida": "00:19",
        "duracion": 100
    },
    {
        "codigo": "IB316",
        "origen": "Pamplona",
        "destino": "Palma de Mallorca",
        "fecha_salida": "2025-03-05",
        "hora_salida": "05:48",
        "duracion": 176
    },
    {
        "codigo": "VY771",
        "origen": "Melilla",
        "destino": "Oviedo",
        "fecha_salida": "2025-03-30",
        "hora_salida": "01:23",
        "duracion": 123
    },
    {
        "codigo": "VY371",
        "origen": "Pamplona",
        "destino": "Santander",
        "fecha_salida": "2025-05-17",
        "hora_salida": "13:56",
        "duracion": 77
    },
    {
        "codigo": "UX864",
        "origen": "Murcia",
        "destino": "Melilla",
        "fecha_salida": "2025-05-23",
        "hora_salida": "00:38",
        "duracion": 134
    },
    {
        "codigo": "UX324",
        "origen": "Vitoria",
        "destino": "Pamplona",
        "fecha_salida": "2025-09-05",
        "hora_salida": "22:20",
        "duracion": 77
    },
    {
        "codigo": "IB873",
        "origen": "Toledo",
        "destino": "Santander",
        "fecha_salida": "2025-10-13",
        "hora_salida": "11:18",
        "duracion": 66
    },
    {
        "codigo": "VY911",
        "origen": "Sevilla",
        "destino": "Malaga",
        "fecha_salida": "2025-03-03",
        "hora_salida": "23:24",
        "duracion": 147
    },
    {
        "codigo": "FR490",
        "origen": "Vitoria",
        "destino": "Valencia",
        "fecha_salida": "2025-09-27",
        "hora_salida": "15:15",
        "duracion": 136
    },
    {
        "codigo": "UX666",
        "origen": "Logrono",
        "destino": "Ceuta",
        "fecha_salida": "2025-05-09",
        "hora_salida": "21:23",
        "duracion": 170
    },
    {
        "codigo": "UX887",
        "origen": "Madrid",
        "destino": "Bilbao",
        "fecha_salida": "2025-11-26",
        "hora_salida": "17:52",
        "duracion": 142
    },
    {
        "codigo": "UX545",
        "origen": "Oviedo",
        "destino": "Sevilla",
        "fecha_salida": "2025-11-01",
        "hora_salida": "01:26",
        "duracion": 80
    },
    {
        "codigo": "UX612",
        "origen": "Logrono",
        "destino": "Madrid",
        "fecha_salida": "2025-11-21",
        "hora_salida": "00:54",
        "duracion": 157
    },
    {
        "codigo": "IB991",
        "origen": "Malaga",
        "destino": "Ceuta",
        "fecha_salida": "2025-09-21",
        "hora_salida": "07:18",
        "duracion": 140
    },
    {
        "codigo": "VY256",
        "origen": "Las Palmas de Gran Canaria",
        "destino": "Ceuta",
        "fecha_salida": "2025-08-03",
        "hora_salida": "14:17",
        "duracion": 107
    },
    {
        "codigo": "IB713",
        "origen": "Malaga",
        "destino": "Melilla",
        "fecha_salida": "2025-05-18",
        "hora_salida": "06:44",
        "duracion": 101
    },
    {
        "codigo": "IB471",
        "origen": "Santander",
        "destino": "Madrid",
        "fecha_salida": "2025-08-15",
        "hora_salida": "03:00",
        "duracion": 172
    },
    {
        "codigo": "IB346",
        "origen": "Las Palmas de Gran Canaria",
        "destino": "Murcia",
        "fecha_salida": "2025-10-08",
        "hora_salida": "12:26",
        "duracion": 172
    },
    {
        "codigo": "IB849",
        "origen": "Melilla",
        "destino": "Valencia",
        "fecha_salida": "2025-06-09",
        "hora_salida": "17:00",
        "duracion": 122
    },
    {
        "codigo": "VY231",
        "origen": "Valencia",
        "destino": "Melilla",
        "fecha_salida": "2026-01-02",
        "hora_salida": "00:31",
        "duracion": 144
    },
    {
        "codigo": "VY371",
        "origen": "Santander",
        "destino": "Melilla",
        "fecha_salida": "2026-01-25",
        "hora_salida": "06:32",
        "duracion": 127
    },
    {
        "codigo": "VY830",
        "origen": "Vitoria",
        "destino": "Zaragoza",
        "fecha_salida": "2025-02-24",
        "hora_salida": "04:39",
        "duracion": 99
    },
    {
        "codigo": "FR629",
        "origen": "Pamplona",
        "destino": "Santa Cruz de Tenerife",
        "fecha_salida": "2025-12-13",
        "hora_salida": "08:40",
        "duracion": 117
    },
    {
        "codigo": "VY165",
        "origen": "Sevilla",
        "destino": "Palma de Mallorca",
        "fecha_salida": "2025-12-31",
        "hora_salida": "14:51",
        "duracion": 103
    },
    {
        "codigo": "VY702",
        "origen": "Madrid",
        "destino": "Melilla",
        "fecha_salida": "2025-04-24",
        "hora_salida": "16:12",
        "duracion": 88
    },
    {
        "codigo": "IB334",
        "origen": "Madrid",
        "destino": "Sevilla",
        "fecha_salida": "2025-11-19",
        "hora_salida": "19:12",
        "duracion": 68
    },
    {
        "codigo": "IB626",
        "origen": "Barcelona",
        "destino": "Santa Cruz de Tenerife",
        "fecha_salida": "2025-08-04",
        "hora_salida": "19:08",
        "duracion": 90
    },
    {
        "codigo": "VY652",
        "origen": "Palma de Mallorca",
        "destino": "Toledo",
        "fecha_salida": "2025-07-03",
        "hora_salida": "19:26",
        "duracion": 76
    },
    {
        "codigo": "VY903",
        "origen": "Melilla",
        "destino": "Santander",
        "fecha_salida": "2025-06-09",
        "hora_salida": "14:01",
        "duracion": 120
    },
    {
        "codigo": "IB199",
        "origen": "Vitoria",
        "destino": "Zaragoza",
        "fecha_salida": "2025-04-23",
        "hora_salida": "01:15",
        "duracion": 144
    },
    {
        "codigo": "FR520",
        "origen": "Vitoria",
        "destino": "Santa Cruz de Tenerife",
        "fecha_salida": "2025-05-16",
        "hora_salida": "06:57",
        "duracion": 119
    },
    {
        "codigo": "IB512",
        "origen": "Barcelona",
        "destino": "Bilbao",
        "fecha_salida": "2025-12-15",
        "hora_salida": "04:21",
        "duracion": 153
    },
    {
        "codigo": "VY296",
        "origen": "Oviedo",
        "destino": "Sevilla",
        "fecha_salida": "2025-07-02",
        "hora_salida": "09:22",
        "duracion": 84
    },
    {
        "codigo": "VY532",
        "origen": "Ceuta",
        "destino": "Logrono",
        "fecha_salida": "2025-04-02",
        "hora_salida": "08:45",
        "duracion": 83
    },
    {
        "codigo": "VY995",
        "origen": "Palma de Mallorca",
        "destino": "Santander",
        "fecha_salida": "2025-03-29",
        "hora_salida": "16:32",
        "duracion": 178
    },
    {
        "codigo": "IB151",
        "origen": "Valencia",
        "destino": "Santander",
        "fecha_salida": "2025-07-19",
        "hora_salida": "05:15",
        "duracion": 143
    },
    {
        "codigo": "IB871",
        "origen": "Ceuta",
        "destino": "Madrid",
        "fecha_salida": "2025-03-31",
        "hora_salida": "05:32",
        "duracion": 168
    },
    {
        "codigo": "FR597",
        "origen": "Murcia",
        "destino": "Malaga",
        "fecha_salida": "2025-07-11",
        "hora_salida": "02:00",
        "duracion": 121
    },
    {
        "codigo": "IB268",
        "origen": "Zaragoza",
        "destino": "Vitoria",
        "fecha_salida": "2026-01-16",
        "hora_salida": "19:18",
        "duracion": 108
    },
    {
        "codigo": "UX902",
        "origen": "Madrid",
        "destino": "Vitoria",
        "fecha_salida": "2025-07-05",
        "hora_salida": "05:58",
        "duracion": 160
    },
    {
        "codigo": "FR813",
        "origen": "Logrono",
        "destino": "Las Palmas de Gran Canaria",
        "fecha_salida": "2025-10-14",
        "hora_salida": "03:13",
        "duracion": 153
    },
    {
        "codigo": "VY294",
        "origen": "Ceuta",
        "destino": "Santander",
        "fecha_salida": "2025-06-04",
        "hora_salida": "09:35",
        "duracion": 97
    },
    {
        "codigo": "IB865",
        "origen": "Zaragoza",
        "destino": "Barcelona",
        "fecha_salida": "2026-01-01",
        "hora_salida": "03:03",
        "duracion": 100
    },
    {
        "codigo": "FR614",
        "origen": "Barcelona",
        "destino": "Valencia",
        "fecha_salida": "2025-03-10",
        "hora_salida": "13:04",
        "duracion": 177
    },
    {
        "codigo": "IB620",
        "origen": "Toledo",
        "destino": "Malaga",
        "fecha_salida": "2025-12-02",
        "hora_salida": "01:40",
        "duracion": 70
    },
    {
        "codigo": "IB791",
        "origen": "Malaga",
        "destino": "Valencia",
        "fecha_salida": "2025-08-19",
        "hora_salida": "02:13",
        "duracion": 170
    },
    {
        "codigo": "IB683",
        "origen": "Murcia",
        "destino": "Vitoria",
        "fecha_salida": "2025-09-17",
        "hora_salida": "22:05",
        "duracion": 91
    },
    {
        "codigo": "IB529",
        "origen": "Melilla",
        "destino": "Barcelona",
        "fecha_salida": "2025-04-11",
        "hora_salida": "03:32",
        "duracion": 144
    },
    {
        "codigo": "UX367",
        "origen": "Melilla",
        "destino": "Toledo",
        "fecha_salida": "2026-02-14",
        "hora_salida": "20:29",
        "duracion": 86
    },
    {
        "codigo": "UX505",
        "origen": "Oviedo",
        "destino": "Murcia",
        "fecha_salida": "2025-07-18",
        "hora_salida": "16:16",
        "duracion": 76
    },
    {
        "codigo": "UX869",
        "origen": "Las Palmas de Gran Canaria",
        "destino": "Santander",
        "fecha_salida": "2025-03-24",
        "hora_salida": "06:33",
        "duracion": 179
    },
    {
        "codigo": "FR736",
        "origen": "Valencia",
        "destino": "Madrid",
        "fecha_salida": "2025-09-24",
        "hora_salida": "01:28",
        "duracion": 132
    },
    {
        "codigo": "VY618",
        "origen": "Sevilla",
        "destino": "Valencia",
        "fecha_salida": "2025-06-15",
        "hora_salida": "12:42",
        "duracion": 93
    },
    {
        "codigo": "IB350",
        "origen": "Bilbao",
        "destino": "Pamplona",
        "fecha_salida": "2026-01-09",
        "hora_salida": "18:41",
        "duracion": 107
    },
    {
        "codigo": "FR953",
        "origen": "Las Palmas de Gran Canaria",
        "destino": "Malaga",
        "fecha_salida": "2025-10-23",
        "hora_salida": "19:25",
        "duracion": 129
    },
    {
        "codigo": "IB783",
        "origen": "Las Palmas de Gran Canaria",
        "destino": "Ceuta",
        "fecha_salida": "2025-10-19",
        "hora_salida": "21:06",
        "duracion": 164
    },
    {
        "codigo": "IB999",
        "origen": "Ceuta",
        "destino": "Las Palmas de Gran Canaria",
        "fecha_salida": "2026-01-31",
        "hora_salida": "13:05",
        "duracion": 77
    },
    {
        "codigo": "IB860",
        "origen": "Palma de Mallorca",
        "destino": "Sevilla",
        "fecha_salida": "2026-01-22",
        "hora_salida": "07:46",
        "duracion": 130
    },
    {
        "codigo": "UX719",
        "origen": "Bilbao",
        "destino": "Las Palmas de Gran Canaria",
        "fecha_salida": "2025-07-12",
        "hora_salida": "02:45",
        "duracion": 86
    },
    {
        "codigo": "UX617",
        "origen": "Oviedo",
        "destino": "Zaragoza",
        "fecha_salida": "2025-10-03",
        "hora_salida": "21:23",
        "duracion": 122
    },
    {
        "codigo": "IB749",
        "origen": "Palma de Mallorca",
        "destino": "Barcelona",
        "fecha_salida": "2025-05-07",
        "hora_salida": "08:20",
        "duracion": 114
    },
    {
        "codigo": "IB441",
        "origen": "Palma de Mallorca",
        "destino": "Barcelona",
        "fecha_salida": "2025-11-22",
        "hora_salida": "07:10",
        "duracion": 158
    },
    {
        "codigo": "VY859",
        "origen": "Bilbao",
        "destino": "Las Palmas de Gran Canaria",
        "fecha_salida": "2025-03-20",
        "hora_salida": "16:23",
        "duracion": 116
    },
    {
        "codigo": "IB214",
        "origen": "Ceuta",
        "destino": "Vitoria",
        "fecha_salida": "2025-03-11",
        "hora_salida": "11:11",
        "duracion": 69
    },
    {
        "codigo": "IB954",
        "origen": "Bilbao",
        "destino": "Melilla",
        "fecha_salida": "2025-11-05",
        "hora_salida": "11:30",
        "duracion": 107
    },
    {
        "codigo": "VY540",
        "origen": "Melilla",
        "destino": "Ceuta",
        "fecha_salida": "2025-05-21",
        "hora_salida": "04:14",
        "duracion": 76
    },
    {
        "codigo": "UX915",
        "origen": "Barcelona",
        "destino": "Oviedo",
        "fecha_salida": "2025-12-18",
        "hora_salida": "21:36",
        "duracion": 170
    },
    {
        "codigo": "VY798",
        "origen": "Barcelona",
        "destino": "Pamplona",
        "fecha_salida": "2025-06-14",
        "hora_salida": "01:22",
        "duracion": 91
    },
    {
        "codigo": "FR735",
        "origen": "Sevilla",
        "destino": "Pamplona",
        "fecha_salida": "2025-03-24",
        "hora_salida": "15:47",
        "duracion": 155
    },
    {
        "codigo": "VY919",
        "origen": "Bilbao",
        "destino": "Palma de Mallorca",
        "fecha_salida": "2026-01-19",
        "hora_salida": "20:13",
        "duracion": 163
    },
    {
        "codigo": "IB283",
        "origen": "Malaga",
        "destino": "Logrono",
        "fecha_salida": "2025-05-23",
        "hora_salida": "01:51",
        "duracion": 154
    },
    {
        "codigo": "VY373",
        "origen": "Oviedo",
        "destino": "Logrono",
        "fecha_salida": "2026-01-24",
        "hora_salida": "04:17",
        "duracion": 80
    },
    {
        "codigo": "IB979",
        "origen": "Sevilla",
        "destino": "Vitoria",
        "fecha_salida": "2025-04-01",
        "hora_salida": "21:29",
        "duracion": 120
    },
    {
        "codigo": "FR458",
        "origen": "Murcia",
        "destino": "Zaragoza",
        "fecha_salida": "2025-07-19",
        "hora_salida": "07:06",
        "duracion": 99
    },
    {
        "codigo": "IB775",
        "origen": "Murcia",
        "destino": "Palma de Mallorca",
        "fecha_salida": "2025-06-09",
        "hora_salida": "14:59",
        "duracion": 84
    },
    {
        "codigo": "UX985",
        "origen": "Pamplona",
        "destino": "Oviedo",
        "fecha_salida": "2025-08-16",
        "hora_salida": "18:10",
        "duracion": 68
    },
    {
        "codigo": "FR795",
        "origen": "Palma de Mallorca",
        "destino": "Pamplona",
        "fecha_salida": "2025-10-26",
        "hora_salida": "13:05",
        "duracion": 167
    },
    {
        "codigo": "IB218",
        "origen": "Ceuta",
        "destino": "Oviedo",
        "fecha_salida": "2026-01-11",
        "hora_salida": "14:33",
        "duracion": 172
    },
    {
        "codigo": "UX139",
        "origen": "Palma de Mallorca",
        "destino": "Malaga",
        "fecha_salida": "2025-07-13",
        "hora_salida": "08:33",
        "duracion": 73
    },
    {
        "codigo": "UX546",
        "origen": "Vitoria",
        "destino": "Santa Cruz de Tenerife",
        "fecha_salida": "2025-04-25",
        "hora_salida": "20:07",
        "duracion": 137
    },
    {
        "codigo": "FR690",
        "origen": "Toledo",
        "destino": "Sevilla",
        "fecha_salida": "2025-07-15",
        "hora_salida": "10:25",
        "duracion": 84
    },
    {
        "codigo": "FR101",
        "origen": "Palma de Mallorca",
        "destino": "Barcelona",
        "fecha_salida": "2025-07-09",
        "hora_salida": "15:26",
        "duracion": 126
    },
    {
        "codigo": "UX541",
        "origen": "Ceuta",
        "destino": "Zaragoza",
        "fecha_salida": "2025-05-14",
        "hora_salida": "00:49",
        "duracion": 68
    },
    {
        "codigo": "IB837",
        "origen": "Oviedo",
        "destino": "Santa Cruz de Tenerife",
        "fecha_salida": "2025-11-08",
        "hora_salida": "22:34",
        "duracion": 175
    },
    {
        "codigo": "UX782",
        "origen": "Las Palmas de Gran Canaria",
        "destino": "Ceuta",
        "fecha_salida": "2025-06-05",
        "hora_salida": "08:29",
        "duracion": 112
    },
    {
        "codigo": "UX667",
        "origen": "Oviedo",
        "destino": "Vitoria",
        "fecha_salida": "2025-11-21",
        "hora_salida": "05:31",
        "duracion": 76
    },
    {
        "codigo": "FR793",
        "origen": "Zaragoza",
        "destino": "Logrono",
        "fecha_salida": "2026-02-20",
        "hora_salida": "10:20",
        "duracion": 155
    },
    {
        "codigo": "FR661",
        "origen": "Malaga",
        "destino": "Oviedo",
        "fecha_salida": "2025-11-14",
        "hora_salida": "03:12",
        "duracion": 166
    },
    {
        "codigo": "UX315",
        "origen": "Madrid",
        "destino": "Oviedo",
        "fecha_salida": "2025-10-31",
        "hora_salida": "08:12",
        "duracion": 115
    },
    {
        "codigo": "FR552",
        "origen": "Melilla",
        "destino": "Oviedo",
        "fecha_salida": "2025-03-21",
        "hora_salida": "09:36",
        "duracion": 116
    },
    {
        "codigo": "FR912",
        "origen": "Zaragoza",
        "destino": "Ceuta",
        "fecha_salida": "2025-10-16",
        "hora_salida": "05:35",
        "duracion": 175
    },
    {
        "codigo": "UX627",
        "origen": "Malaga",
        "destino": "Valencia",
        "fecha_salida": "2025-10-26",
        "hora_salida": "06:30",
        "duracion": 144
    },
    {
        "codigo": "VY788",
        "origen": "Oviedo",
        "destino": "Valencia",
        "fecha_salida": "2025-04-29",
        "hora_salida": "03:12",
        "duracion": 99
    },
    {
        "codigo": "VY125",
        "origen": "Murcia",
        "destino": "Zaragoza",
        "fecha_salida": "2025-09-17",
        "hora_salida": "02:37",
        "duracion": 65
    },
    {
        "codigo": "IB566",
        "origen": "Murcia",
        "destino": "Toledo",
        "fecha_salida": "2025-12-01",
        "hora_salida": "20:02",
        "duracion": 113
    },
    {
        "codigo": "FR606",
        "origen": "Melilla",
        "destino": "Zaragoza",
        "fecha_salida": "2025-05-27",
        "hora_salida": "17:53",
        "duracion": 111
    },
    {
        "codigo": "IB868",
        "origen": "Murcia",
        "destino": "Bilbao",
        "fecha_salida": "2025-04-26",
        "hora_salida": "03:06",
        "duracion": 170
    },
    {
        "codigo": "VY280",
        "origen": "Sevilla",
        "destino": "Logrono",
        "fecha_salida": "2025-08-20",
        "hora_salida": "04:39",
        "duracion": 162
    },
    {
        "codigo": "IB670",
        "origen": "Toledo",
        "destino": "Logrono",
        "fecha_salida": "2025-07-19",
        "hora_salida": "00:51",
        "duracion": 91
    },
    {
        "codigo": "VY920",
        "origen": "Sevilla",
        "destino": "Santander",
        "fecha_salida": "2025-06-06",
        "hora_salida": "12:10",
        "duracion": 119
    },
    {
        "codigo": "UX873",
        "origen": "Toledo",
        "destino": "Melilla",
        "fecha_salida": "2026-02-16",
        "hora_salida": "01:21",
        "duracion": 174
    },
    {
        "codigo": "FR950",
        "origen": "Logrono",
        "destino": "Ceuta",
        "fecha_salida": "2025-10-28",
        "hora_salida": "05:18",
        "duracion": 176
    },
    {
        "codigo": "VY861",
        "origen": "Ceuta",
        "destino": "Logrono",
        "fecha_salida": "2025-11-15",
        "hora_salida": "22:13",
        "duracion": 170
    },
    {
        "codigo": "UX869",
        "origen": "Santander",
        "destino": "Logrono",
        "fecha_salida": "2025-09-25",
        "hora_salida": "23:13",
        "duracion": 91
    },
    {
        "codigo": "FR741",
        "origen": "Palma de Mallorca",
        "destino": "Ceuta",
        "fecha_salida": "2025-05-17",
        "hora_salida": "23:02",
        "duracion": 90
    },
    {
        "codigo": "IB830",
        "origen": "Palma de Mallorca",
        "destino": "Santander",
        "fecha_salida": "2025-11-14",
        "hora_salida": "13:09",
        "duracion": 96
    },
    {
        "codigo": "UX427",
        "origen": "Murcia",
        "destino": "Las Palmas de Gran Canaria",
        "fecha_salida": "2025-06-27",
        "hora_salida": "14:37",
        "duracion": 174
    },
    {
        "codigo": "VY254",
        "origen": "Ceuta",
        "destino": "Valencia",
        "fecha_salida": "2026-01-15",
        "hora_salida": "00:01",
        "duracion": 89
    },
    {
        "codigo": "VY165",
        "origen": "Pamplona",
        "destino": "Bilbao",
        "fecha_salida": "2025-12-17",
        "hora_salida": "01:17",
        "duracion": 113
    },
    {
        "codigo": "FR525",
        "origen": "Vitoria",
        "destino": "Oviedo",
        "fecha_salida": "2025-12-20",
        "hora_salida": "00:55",
        "duracion": 67
    },
    {
        "codigo": "FR888",
        "origen": "Zaragoza",
        "destino": "Logrono",
        "fecha_salida": "2025-03-15",
        "hora_salida": "09:27",
        "duracion": 134
    },
    {
        "codigo": "FR106",
        "origen": "Madrid",
        "destino": "Vitoria",
        "fecha_salida": "2025-05-21",
        "hora_salida": "14:57",
        "duracion": 180
    },
    {
        "codigo": "FR973",
        "origen": "Santa Cruz de Tenerife",
        "destino": "Las Palmas de Gran Canaria",
        "fecha_salida": "2026-01-06",
        "hora_salida": "19:50",
        "duracion": 174
    },
    {
        "codigo": "VY599",
        "origen": "Vitoria",
        "destino": "Melilla",
        "fecha_salida": "2025-03-06",
        "hora_salida": "03:16",
        "duracion": 88
    },
    {
        "codigo": "FR129",
        "origen": "Palma de Mallorca",
        "destino": "Logrono",
        "fecha_salida": "2025-12-31",
        "hora_salida": "07:39",
        "duracion": 109
    },
    {
        "codigo": "VY960",
        "origen": "Oviedo",
        "destino": "Vitoria",
        "fecha_salida": "2025-06-24",
        "hora_salida": "04:19",
        "duracion": 119
    },
    {
        "codigo": "IB503",
        "origen": "Bilbao",
        "destino": "Melilla",
        "fecha_salida": "2025-07-27",
        "hora_salida": "11:12",
        "duracion": 135
    },
    {
        "codigo": "IB758",
        "origen": "Melilla",
        "destino": "Madrid",
        "fecha_salida": "2025-06-05",
        "hora_salida": "15:36",
        "duracion": 114
    },
    {
        "codigo": "VY151",
        "origen": "Bilbao",
        "destino": "Santander",
        "fecha_salida": "2025-03-19",
        "hora_salida": "09:00",
        "duracion": 93
    },
    {
        "codigo": "VY565",
        "origen": "Pamplona",
        "destino": "Oviedo",
        "fecha_salida": "2025-05-14",
        "hora_salida": "14:35",
        "duracion": 101
    },
    {
        "codigo": "UX870",
        "origen": "Oviedo",
        "destino": "Vitoria",
        "fecha_salida": "2026-02-11",
        "hora_salida": "07:07",
        "duracion": 166
    },
    {
        "codigo": "IB581",
        "origen": "Vitoria",
        "destino": "Palma de Mallorca",
        "fecha_salida": "2025-09-29",
        "hora_salida": "22:35",
        "duracion": 62
    },
    {
        "codigo": "UX329",
        "origen": "Ceuta",
        "destino": "Barcelona",
        "fecha_salida": "2026-01-28",
        "hora_salida": "00:25",
        "duracion": 143
    },
    {
        "codigo": "IB353",
        "origen": "Valencia",
        "destino": "Barcelona",
        "fecha_salida": "2025-11-27",
        "hora_salida": "11:31",
        "duracion": 85
    },
    {
        "codigo": "VY229",
        "origen": "Madrid",
        "destino": "Malaga",
        "fecha_salida": "2025-06-23",
        "hora_salida": "21:05",
        "duracion": 120
    },
    {
        "codigo": "FR816",
        "origen": "Sevilla",
        "destino": "Murcia",
        "fecha_salida": "2025-05-15",
        "hora_salida": "05:54",
        "duracion": 92
    },
    {
        "codigo": "IB896",
        "origen": "Santa Cruz de Tenerife",
        "destino": "Malaga",
        "fecha_salida": "2025-11-03",
        "hora_salida": "05:12",
        "duracion": 164
    },
    {
        "codigo": "IB692",
        "origen": "Malaga",
        "destino": "Oviedo",
        "fecha_salida": "2025-09-03",
        "hora_salida": "13:15",
        "duracion": 63
    },
    {
        "codigo": "FR832",
        "origen": "Las Palmas de Gran Canaria",
        "destino": "Vitoria",
        "fecha_salida": "2025-07-25",
        "hora_salida": "07:38",
        "duracion": 85
    },
    {
        "codigo": "IB813",
        "origen": "Valencia",
        "destino": "Palma de Mallorca",
        "fecha_salida": "2026-01-31",
        "hora_salida": "05:55",
        "duracion": 158
    },
    {
        "codigo": "IB455",
        "origen": "Las Palmas de Gran Canaria",
        "destino": "Sevilla",
        "fecha_salida": "2026-02-11",
        "hora_salida": "20:17",
        "duracion": 128
    },
    {
        "codigo": "IB618",
        "origen": "Vitoria",
        "destino": "Santa Cruz de Tenerife",
        "fecha_salida": "2025-10-29",
        "hora_salida": "07:53",
        "duracion": 142
    },
    {
        "codigo": "FR942",
        "origen": "Oviedo",
        "destino": "Madrid",
        "fecha_salida": "2025-08-18",
        "hora_salida": "20:53",
        "duracion": 122
    },
    {
        "codigo": "UX750",
        "origen": "Sevilla",
        "destino": "Logrono",
        "fecha_salida": "2025-04-18",
        "hora_salida": "03:44",
        "duracion": 174
    },
    {
        "codigo": "FR280",
        "origen": "Logrono",
        "destino": "Bilbao",
        "fecha_salida": "2025-06-04",
        "hora_salida": "12:56",
        "duracion": 153
    },
    {
        "codigo": "FR576",
        "origen": "Toledo",
        "destino": "Palma de Mallorca",
        "fecha_salida": "2025-04-16",
        "hora_salida": "21:31",
        "duracion": 115
    },
    {
        "codigo": "UX972",
        "origen": "Melilla",
        "destino": "Palma de Mallorca",
        "fecha_salida": "2025-05-28",
        "hora_salida": "10:49",
        "duracion": 91
    },
    {
        "codigo": "FR349",
        "origen": "Valencia",
        "destino": "Las Palmas de Gran Canaria",
        "fecha_salida": "2025-12-07",
        "hora_salida": "23:53",
        "duracion": 156
    },
    {
        "codigo": "UX129",
        "origen": "Logrono",
        "destino": "Pamplona",
        "fecha_salida": "2025-09-27",
        "hora_salida": "16:24",
        "duracion": 123
    },
    {
        "codigo": "FR317",
        "origen": "Oviedo",
        "destino": "Malaga",
        "fecha_salida": "2025-09-18",
        "hora_salida": "23:42",
        "duracion": 105
    },
    {
        "codigo": "UX710",
        "origen": "Palma de Mallorca",
        "destino": "Santa Cruz de Tenerife",
        "fecha_salida": "2025-06-03",
        "hora_salida": "17:00",
        "duracion": 149
    },
    {
        "codigo": "IB629",
        "origen": "Palma de Mallorca",
        "destino": "Melilla",
        "fecha_salida": "2025-12-08",
        "hora_salida": "18:45",
        "duracion": 84
    },
    {
        "codigo": "FR600",
        "origen": "Valencia",
        "destino": "Palma de Mallorca",
        "fecha_salida": "2025-10-06",
        "hora_salida": "16:49",
        "duracion": 131
    },
    {
        "codigo": "FR558",
        "origen": "Murcia",
        "destino": "Toledo",
        "fecha_salida": "2025-08-07",
        "hora_salida": "01:22",
        "duracion": 161
    },
    {
        "codigo": "UX326",
        "origen": "Madrid",
        "destino": "Sevilla",
        "fecha_salida": "2026-02-05",
        "hora_salida": "08:23",
        "duracion": 111
    },
    {
        "codigo": "UX584",
        "origen": "Murcia",
        "destino": "Oviedo",
        "fecha_salida": "2025-10-06",
        "hora_salida": "07:00",
        "duracion": 130
    },
    {
        "codigo": "FR863",
        "origen": "Toledo",
        "destino": "Santa Cruz de Tenerife",
        "fecha_salida": "2025-07-26",
        "hora_salida": "18:45",
        "duracion": 130
    },
    {
        "codigo": "FR377",
        "origen": "Oviedo",
        "destino": "Pamplona",
        "fecha_salida": "2025-07-12",
        "hora_salida": "06:08",
        "duracion": 99
    },
    {
        "codigo": "IB838",
        "origen": "Palma de Mallorca",
        "destino": "Murcia",
        "fecha_salida": "2025-05-17",
        "hora_salida": "20:18",
        "duracion": 84
    },
    {
        "codigo": "VY296",
        "origen": "Oviedo",
        "destino": "Sevilla",
        "fecha_salida": "2025-04-16",
        "hora_salida": "09:25",
        "duracion": 87
    },
    {
        "codigo": "UX202",
        "origen": "Santander",
        "destino": "Palma de Mallorca",
        "fecha_salida": "2025-09-07",
        "hora_salida": "13:12",
        "duracion": 166
    },
    {
        "codigo": "VY469",
        "origen": "Zaragoza",
        "destino": "Oviedo",
        "fecha_salida": "2025-09-01",
        "hora_salida": "07:59",
        "duracion": 82
    },
    {
        "codigo": "VY380",
        "origen": "Las Palmas de Gran Canaria",
        "destino": "Madrid",
        "fecha_salida": "2025-03-28",
        "hora_salida": "23:25",
        "duracion": 65
    },
    {
        "codigo": "UX814",
        "origen": "Barcelona",
        "destino": "Melilla",
        "fecha_salida": "2025-12-12",
        "hora_salida": "04:28",
        "duracion": 180
    },
    {
        "codigo": "IB993",
        "origen": "Bilbao",
        "destino": "Toledo",
        "fecha_salida": "2025-03-11",
        "hora_salida": "23:14",
        "duracion": 61
    },
    {
        "codigo": "FR590",
        "origen": "Melilla",
        "destino": "Las Palmas de Gran Canaria",
        "fecha_salida": "2026-01-22",
        "hora_salida": "02:08",
        "duracion": 116
    },
    {
        "codigo": "IB358",
        "origen": "Oviedo",
        "destino": "Malaga",
        "fecha_salida": "2025-04-05",
        "hora_salida": "06:05",
        "duracion": 180
    },
    {
        "codigo": "IB510",
        "origen": "Santander",
        "destino": "Sevilla",
        "fecha_salida": "2025-04-22",
        "hora_salida": "00:40",
        "duracion": 122
    },
    {
        "codigo": "VY252",
        "origen": "Valencia",
        "destino": "Barcelona",
        "fecha_salida": "2025-10-23",
        "hora_salida": "08:18",
        "duracion": 163
    },
    {
        "codigo": "IB354",
        "origen": "Melilla",
        "destino": "Las Palmas de Gran Canaria",
        "fecha_salida": "2025-04-24",
        "hora_salida": "19:13",
        "duracion": 75
    },
    {
        "codigo": "VY894",
        "origen": "Ceuta",
        "destino": "Vitoria",
        "fecha_salida": "2025-12-26",
        "hora_salida": "06:47",
        "duracion": 126
    },
    {
        "codigo": "FR404",
        "origen": "Pamplona",
        "destino": "Santander",
        "fecha_salida": "2025-11-12",
        "hora_salida": "22:37",
        "duracion": 170
    },
    {
        "codigo": "UX682",
        "origen": "Melilla",
        "destino": "Vitoria",
        "fecha_salida": "2025-08-04",
        "hora_salida": "14:53",
        "duracion": 139
    },
    {
        "codigo": "VY740",
        "origen": "Barcelona",
        "destino": "Bilbao",
        "fecha_salida": "2025-10-11",
        "hora_salida": "07:01",
        "duracion": 87
    },
    {
        "codigo": "VY345",
        "origen": "Palma de Mallorca",
        "destino": "Valencia",
        "fecha_salida": "2025-03-18",
        "hora_salida": "08:12",
        "duracion": 82
    },
    {
        "codigo": "VY102",
        "origen": "Ceuta",
        "destino": "Valencia",
        "fecha_salida": "2025-07-21",
        "hora_salida": "02:22",
        "duracion": 112
    },
    {
        "codigo": "UX133",
        "origen": "Logrono",
        "destino": "Toledo",
        "fecha_salida": "2025-07-19",
        "hora_salida": "21:01",
        "duracion": 89
    },
    {
        "codigo": "FR172",
        "origen": "Las Palmas de Gran Canaria",
        "destino": "Oviedo",
        "fecha_salida": "2025-10-11",
        "hora_salida": "02:09",
        "duracion": 147
    },
    {
        "codigo": "VY535",
        "origen": "Murcia",
        "destino": "Las Palmas de Gran Canaria",
        "fecha_salida": "2025-08-22",
        "hora_salida": "10:37",
        "duracion": 74
    },
    {
        "codigo": "VY372",
        "origen": "Ceuta",
        "destino": "Murcia",
        "fecha_salida": "2025-09-15",
        "hora_salida": "03:47",
        "duracion": 165
    },
    {
        "codigo": "IB269",
        "origen": "Bilbao",
        "destino": "Valencia",
        "fecha_salida": "2025-05-30",
        "hora_salida": "07:25",
        "duracion": 161
    },
    {
        "codigo": "FR227",
        "origen": "Las Palmas de Gran Canaria",
        "destino": "Oviedo",
        "fecha_salida": "2025-09-24",
        "hora_salida": "12:31",
        "duracion": 119
    },
    {
        "codigo": "UX612",
        "origen": "Las Palmas de Gran Canaria",
        "destino": "Vitoria",
        "fecha_salida": "2026-01-21",
        "hora_salida": "23:07",
        "duracion": 129
    },
    {
        "codigo": "IB712",
        "origen": "Santander",
        "destino": "Logrono",
        "fecha_salida": "2025-02-26",
        "hora_salida": "03:05",
        "duracion": 65
    },
    {
        "codigo": "UX126",
        "origen": "Vitoria",
        "destino": "Oviedo",
        "fecha_salida": "2025-11-12",
        "hora_salida": "20:47",
        "duracion": 71
    },
    {
        "codigo": "UX690",
        "origen": "Murcia",
        "destino": "Madrid",
        "fecha_salida": "2025-11-28",
        "hora_salida": "13:41",
        "duracion": 65
    },
    {
        "codigo": "FR384",
        "origen": "Malaga",
        "destino": "Toledo",
        "fecha_salida": "2025-04-07",
        "hora_salida": "03:46",
        "duracion": 83
    },
    {
        "codigo": "FR193",
        "origen": "Melilla",
        "destino": "Vitoria",
        "fecha_salida": "2025-11-13",
        "hora_salida": "10:05",
        "duracion": 120
    },
    {
        "codigo": "UX428",
        "origen": "Santa Cruz de Tenerife",
        "destino": "Logrono",
        "fecha_salida": "2026-01-31",
        "hora_salida": "06:54",
        "duracion": 145
    },
    {
        "codigo": "UX521",
        "origen": "Sevilla",
        "destino": "Zaragoza",
        "fecha_salida": "2025-09-18",
        "hora_salida": "05:00",
        "duracion": 148
    },
    {
        "codigo": "FR933",
        "origen": "Santander",
        "destino": "Las Palmas de Gran Canaria",
        "fecha_salida": "2025-12-10",
        "hora_salida": "06:46",
        "duracion": 157
    },
    {
        "codigo": "FR190",
        "origen": "Ceuta",
        "destino": "Barcelona",
        "fecha_salida": "2025-06-05",
        "hora_salida": "07:04",
        "duracion": 100
    },
    {
        "codigo": "IB891",
        "origen": "Palma de Mallorca",
        "destino": "Santa Cruz de Tenerife",
        "fecha_salida": "2025-12-17",
        "hora_salida": "03:56",
        "duracion": 111
    },
    {
        "codigo": "FR523",
        "origen": "Toledo",
        "destino": "Madrid",
        "fecha_salida": "2025-10-28",
        "hora_salida": "14:16",
        "duracion": 66
    },
    {
        "codigo": "UX737",
        "origen": "Zaragoza",
        "destino": "Ceuta",
        "fecha_salida": "2025-07-03",
        "hora_salida": "18:44",
        "duracion": 156
    },
    {
        "codigo": "IB308",
        "origen": "Santander",
        "destino": "Logrono",
        "fecha_salida": "2025-04-05",
        "hora_salida": "23:49",
        "duracion": 94
    },
    {
        "codigo": "UX548",
        "origen": "Ceuta",
        "destino": "Bilbao",
        "fecha_salida": "2025-06-15",
        "hora_salida": "15:42",
        "duracion": 172
    },
    {
        "codigo": "IB745",
        "origen": "Santander",
        "destino": "Sevilla",
        "fecha_salida": "2025-08-09",
        "hora_salida": "12:23",
        "duracion": 137
    },
    {
        "codigo": "UX664",
        "origen": "Murcia",
        "destino": "Malaga",
        "fecha_salida": "2025-04-24",
        "hora_salida": "02:13",
        "duracion": 61
    },
    {
        "codigo": "IB330",
        "origen": "Ceuta",
        "destino": "Vitoria",
        "fecha_salida": "2025-08-16",
        "hora_salida": "21:05",
        "duracion": 167
    },
    {
        "codigo": "IB763",
        "origen": "Sevilla",
        "destino": "Santander",
        "fecha_salida": "2025-02-22",
        "hora_salida": "22:19",
        "duracion": 166
    },
    {
        "codigo": "UX621",
        "origen": "Bilbao",
        "destino": "Toledo",
        "fecha_salida": "2025-11-29",
        "hora_salida": "02:28",
        "duracion": 150
    },
    {
        "codigo": "FR583",
        "origen": "Palma de Mallorca",
        "destino": "Logrono",
        "fecha_salida": "2026-01-27",
        "hora_salida": "19:37",
        "duracion": 91
    },
    {
        "codigo": "VY492",
        "origen": "Logrono",
        "destino": "Melilla",
        "fecha_salida": "2025-11-28",
        "hora_salida": "03:59",
        "duracion": 84
    },
    {
        "codigo": "IB382",
        "origen": "Toledo",
        "destino": "Bilbao",
        "fecha_salida": "2025-06-03",
        "hora_salida": "23:02",
        "duracion": 158
    },
    {
        "codigo": "UX940",
        "origen": "Vitoria",
        "destino": "Oviedo",
        "fecha_salida": "2025-09-04",
        "hora_salida": "01:53",
        "duracion": 60
    },
    {
        "codigo": "FR986",
        "origen": "Las Palmas de Gran Canaria",
        "destino": "Oviedo",
        "fecha_salida": "2025-12-14",
        "hora_salida": "14:05",
        "duracion": 79
    },
    {
        "codigo": "FR453",
        "origen": "Logrono",
        "destino": "Melilla",
        "fecha_salida": "2025-05-02",
        "hora_salida": "01:14",
        "duracion": 102
    },
    {
        "codigo": "FR566",
        "origen": "Ceuta",
        "destino": "Melilla",
        "fecha_salida": "2025-09-06",
        "hora_salida": "20:01",
        "duracion": 179
    },
    {
        "codigo": "VY685",
        "origen": "Oviedo",
        "destino": "Zaragoza",
        "fecha_salida": "2026-02-11",
        "hora_salida": "02:23",
        "duracion": 109
    },
    {
        "codigo": "IB425",
        "origen": "Murcia",
        "destino": "Logrono",
        "fecha_salida": "2025-04-03",
        "hora_salida": "23:54",
        "duracion": 155
    },
    {
        "codigo": "FR779",
        "origen": "Santander",
        "destino": "Pamplona",
        "fecha_salida": "2026-01-25",
        "hora_salida": "17:54",
        "duracion": 161
    },
    {
        "codigo": "IB229",
        "origen": "Bilbao",
        "destino": "Toledo",
        "fecha_salida": "2025-10-22",
        "hora_salida": "12:18",
        "duracion": 124
    },
    {
        "codigo": "IB995",
        "origen": "Melilla",
        "destino": "Oviedo",
        "fecha_salida": "2025-06-17",
        "hora_salida": "13:47",
        "duracion": 168
    },
    {
        "codigo": "FR115",
        "origen": "Logrono",
        "destino": "Sevilla",
        "fecha_salida": "2026-01-14",
        "hora_salida": "13:00",
        "duracion": 152
    },
    {
        "codigo": "VY176",
        "origen": "Bilbao",
        "destino": "Logrono",
        "fecha_salida": "2025-10-27",
        "hora_salida": "19:31",
        "duracion": 120
    },
    {
        "codigo": "FR765",
        "origen": "Palma de Mallorca",
        "destino": "Santa Cruz de Tenerife",
        "fecha_salida": "2025-09-06",
        "hora_salida": "19:50",
        "duracion": 70
    },
    {
        "codigo": "FR424",
        "origen": "Oviedo",
        "destino": "Melilla",
        "fecha_salida": "2025-10-16",
        "hora_salida": "04:05",
        "duracion": 140
    },
    {
        "codigo": "IB732",
        "origen": "Santander",
        "destino": "Melilla",
        "fecha_salida": "2025-05-09",
        "hora_salida": "22:04",
        "duracion": 68
    },
    {
        "codigo": "VY864",
        "origen": "Murcia",
        "destino": "Oviedo",
        "fecha_salida": "2025-04-22",
        "hora_salida": "00:38",
        "duracion": 71
    },
    {
        "codigo": "IB554",
        "origen": "Vitoria",
        "destino": "Sevilla",
        "fecha_salida": "2025-07-16",
        "hora_salida": "21:12",
        "duracion": 81
    },
    {
        "codigo": "IB432",
        "origen": "Las Palmas de Gran Canaria",
        "destino": "Madrid",
        "fecha_salida": "2025-12-14",
        "hora_salida": "19:11",
        "duracion": 161
    },
    {
        "codigo": "UX483",
        "origen": "Barcelona",
        "destino": "Oviedo",
        "fecha_salida": "2025-04-25",
        "hora_salida": "09:49",
        "duracion": 115
    },
    {
        "codigo": "FR679",
        "origen": "Bilbao",
        "destino": "Palma de Mallorca",
        "fecha_salida": "2025-09-19",
        "hora_salida": "03:27",
        "duracion": 147
    },
    {
        "codigo": "VY180",
        "origen": "Malaga",
        "destino": "Zaragoza",
        "fecha_salida": "2025-12-21",
        "hora_salida": "01:24",
        "duracion": 138
    },
    {
        "codigo": "FR697",
        "origen": "Pamplona",
        "destino": "Murcia",
        "fecha_salida": "2026-02-14",
        "hora_salida": "21:47",
        "duracion": 78
    },
    {
        "codigo": "UX570",
        "origen": "Murcia",
        "destino": "Santander",
        "fecha_salida": "2025-09-15",
        "hora_salida": "15:20",
        "duracion": 92
    },
    {
        "codigo": "UX793",
        "origen": "Madrid",
        "destino": "Santander",
        "fecha_salida": "2026-02-13",
        "hora_salida": "09:03",
        "duracion": 129
    },
    {
        "codigo": "FR453",
        "origen": "Malaga",
        "destino": "Valencia",
        "fecha_salida": "2025-02-21",
        "hora_salida": "21:24",
        "duracion": 135
    },
    {
        "codigo": "UX567",
        "origen": "Las Palmas de Gran Canaria",
        "destino": "Logrono",
        "fecha_salida": "2025-10-12",
        "hora_salida": "06:39",
        "duracion": 168
    },
    {
        "codigo": "FR973",
        "origen": "Las Palmas de Gran Canaria",
        "destino": "Zaragoza",
        "fecha_salida": "2025-06-27",
        "hora_salida": "13:26",
        "duracion": 121
    },
    {
        "codigo": "FR685",
        "origen": "Sevilla",
        "destino": "Palma de Mallorca",
        "fecha_salida": "2025-08-30",
        "hora_salida": "10:13",
        "duracion": 105
    },
    {
        "codigo": "UX122",
        "origen": "Melilla",
        "destino": "Las Palmas de Gran Canaria",
        "fecha_salida": "2025-03-01",
        "hora_salida": "05:37",
        "duracion": 166
    },
    {
        "codigo": "IB679",
        "origen": "Pamplona",
        "destino": "Palma de Mallorca",
        "fecha_salida": "2025-04-06",
        "hora_salida": "02:45",
        "duracion": 170
    },
    {
        "codigo": "UX894",
        "origen": "Barcelona",
        "destino": "Toledo",
        "fecha_salida": "2026-02-17",
        "hora_salida": "11:54",
        "duracion": 162
    },
    {
        "codigo": "VY751",
        "origen": "Murcia",
        "destino": "Pamplona",
        "fecha_salida": "2025-07-12",
        "hora_salida": "15:18",
        "duracion": 84
    },
    {
        "codigo": "IB742",
        "origen": "Palma de Mallorca",
        "destino": "Bilbao",
        "fecha_salida": "2026-01-28",
        "hora_salida": "22:21",
        "duracion": 142
    },
    {
        "codigo": "FR134",
        "origen": "Barcelona",
        "destino": "Oviedo",
        "fecha_salida": "2026-01-10",
        "hora_salida": "15:46",
        "duracion": 134
    },
    {
        "codigo": "IB402",
        "origen": "Santa Cruz de Tenerife",
        "destino": "Bilbao",
        "fecha_salida": "2025-12-31",
        "hora_salida": "23:46",
        "duracion": 101
    },
    {
        "codigo": "VY235",
        "origen": "Vitoria",
        "destino": "Malaga",
        "fecha_salida": "2025-06-21",
        "hora_salida": "02:19",
        "duracion": 160
    },
    {
        "codigo": "UX950",
        "origen": "Ceuta",
        "destino": "Santa Cruz de Tenerife",
        "fecha_salida": "2025-05-25",
        "hora_salida": "15:56",
        "duracion": 81
    },
    {
        "codigo": "UX864",
        "origen": "Palma de Mallorca",
        "destino": "Toledo",
        "fecha_salida": "2025-03-16",
        "hora_salida": "03:59",
        "duracion": 171
    },
    {
        "codigo": "FR177",
        "origen": "Oviedo",
        "destino": "Sevilla",
        "fecha_salida": "2025-05-26",
        "hora_salida": "05:10",
        "duracion": 78
    }
]